caddo_file_parser/__init__.py
caddo_file_parser/caddo_file_parser.py
caddo_file_parser/models/__init__.py
caddo_file_parser/models/caddo_file.py
caddo_file_parser/models/index_set.py
caddo_file_parser/models/run.py
caddo_file_parser/settings/generation_settings.py
caddo_file_parser/settings/generation_settings_loader.py
caddo_file_parser/test/__init__.py
caddo_file_parser/test/file_reading_test.py
caddo_file_parser/test/file_saving_test.py
caddo_file_parser/test/settings_loader_test.py
caddo_file_parser/validation/__init__.py
caddo_file_parser/validation/caddo_file_validator.py
caddo_file_parser/validation/settings_validator.py
caddo_file_parser-0.46.1.dist-info/METADATA
caddo_file_parser-0.46.1.dist-info/WHEEL
caddo_file_parser-0.46.1.dist-info/top_level.txt
caddo_file_parser-0.46.1.dist-info/RECORD
