Metadata-Version: 2.1
Name: caddo-file-parser
Version: 0.46.1
Summary: File parser for CaddoBenchmark Project
Author-email: Piotr Tylczyński <piotr@ptl.cloud>, Katarzyna Kulesa <katarzyna.kulesa@kasiait.pl>
Classifier: Programming Language :: Python :: 3
Classifier: License :: OSI Approved :: MIT License
Classifier: Operating System :: OS Independent
Requires-Python: >=3.7
Requires-Dist: pandas
Requires-Dist: pyyaml
Requires-Dist: numpy
